pyipsw/__init__.py
pyipsw/__main__.py
pyipsw/cli.py
pyipsw/pyipsw.py
pyipsw-0.0.2.dist-info/LICENSE
pyipsw-0.0.2.dist-info/METADATA
pyipsw-0.0.2.dist-info/WHEEL
pyipsw-0.0.2.dist-info/entry_points.txt
pyipsw-0.0.2.dist-info/top_level.txt
pyipsw-0.0.2.dist-info/RECORD
