Metadata-Version: 2.1
Name: pyipsw
Version: 0.0.2
Summary: utility created in order to access ipsw.me data easily using python/cli
Author-email: matan1008 <matan1008@gmail.com>
Maintainer-email: matan1008 <matan1008@gmail.com>
License: MIT License
Project-URL: Homepage, https://github.com/matan1008/pyipsw
Project-URL: Bug Reports, https://github.com/matan1008/pyipsw/issues
Keywords: ios,ipsw,firmware,cli
Classifier: Development Status :: 5 - Production/Stable
Classifier: License :: OSI Approved :: GNU General Public License v3 or later (GPLv3+)
Classifier: Programming Language :: Python :: 3
Classifier: Programming Language :: Python :: 3.8
Classifier: Programming Language :: Python :: 3.9
Classifier: Programming Language :: Python :: 3.10
Classifier: Programming Language :: Python :: 3.11
Classifier: Programming Language :: Python :: 3 :: Only
Requires-Python: >=3.8
License-File: LICENSE
Requires-Dist: humanfriendly
Requires-Dist: click
Requires-Dist: requests
Requires-Dist: tqdm
Requires-Dist: setuptools
Provides-Extra: test
Requires-Dist: pytest ; extra == 'test'
